[
{
"id" : 1,
"languageID" : 1,
"language" : "French",
"title" : "numbers",
"question" : "Would you like to read a fun story or play a cool game?",
"fillintheBlank": [
    {
        "sampleSentence" : "Five in french is ___.",
        "wordBank" :["une", "cinq", "sept", "neuf"],
        "userInput": "sept"
    }
],
"currentCategory" : "numbers",
"totalQuestionsAnswered" : 1,
"numCorrectAnswers" : 1,
"missedWords" : []
}, 

{
"id" : 2,
"languageID" : 2,
"language" : "Spanish",
"title" : "colors",
"question" : "Would you like to read a fun story or play a cool game?",
"flashcard": [
    {
        "words" :["jaune", "bleu", "rouge", "noir", "vert"],
        "word": "rouge",
        "pronunciation" : "roozh",
        "translation" : "red" 
    }
],
"currentCategory" : "colors",
"totalQuestionsAnswered" : 1,
"progressInCategory" : 17
}
]